agent_pods_sdk/__init__.py
agent_pods_sdk/base_tools/__init__.py
agent_pods_sdk/base_tools/datasources_tool/datasources_tool.py
agent_pods_sdk/base_tools/datasources_tool/json_schema_hybrid_search.py
agent_pods_sdk/templates/__init__.py
agent_pods_sdk/templates/agent_pods.py
agent_pods_sdk/utils/__init__.py
agent_pods_sdk-0.1.1.dist-info/METADATA
agent_pods_sdk-0.1.1.dist-info/WHEEL
agent_pods_sdk-0.1.1.dist-info/top_level.txt
agent_pods_sdk-0.1.1.dist-info/RECORD
