Metadata-Version: 2.4
Name: agent-pods-sdk
Version: 0.1.1
Summary: A simple SDK for deploying agent pods using FastAPI and SSE.
Requires-Python: >=3.12
Requires-Dist: loguru
Requires-Dist: types-setuptools
Requires-Dist: uvicorn
Requires-Dist: fastapi
Requires-Dist: python-dotenv
Requires-Dist: sse-starlette
Requires-Dist: openai_agents
